plugs_status/__init__.py
plugs_status/apps.py
plugs_status/models.py
plugs_status/settings.py
plugs_status/urls.py
plugs_status/utils.py
plugs_status/views.py
plugs_status/static/css/plugs_status.css
plugs_status/static/js/plugs_status.js
plugs_status/templates/plugs_status/base.html
plugs_status-0.2.0.dist-info/DESCRIPTION.rst
plugs_status-0.2.0.dist-info/METADATA
plugs_status-0.2.0.dist-info/RECORD
plugs_status-0.2.0.dist-info/WHEEL
plugs_status-0.2.0.dist-info/metadata.json
plugs_status-0.2.0.dist-info/top_level.txt
