Metadata-Version: 2.0
Name: plugs-status
Version: 0.2.0
Summary: API Status endpoint
Home-page: https://github.com/solocompt/plugs-status
Author: Solo
Author-email: geral@solo.com.pt
License: MIT
Keywords: plugs-status
Platform: UNKNOWN
Classifier: Development Status :: 3 - Alpha
Classifier: Framework :: Django :: 1.11
Classifier: Intended Audience :: Developers
Classifier: License :: OSI Approved :: MIT License
Classifier: Natural Language :: English
Classifier: Programming Language :: Python :: 3
